Metadata-Version: 2.1
Name: odoo-addon-purchase_request_analytic
Version: 17.0.1.0.0.3
Requires-Python: >=3.10
Requires-Dist: odoo-addon-purchase_request>=17.0dev,<17.1dev
Requires-Dist: odoo>=17.0a,<17.1dev
Summary: Purchase Request Analytic
Home-page: https://github.com/OCA/account-analytic
License: AGPL-3
Author: ForgeFlow, Odoo Community Association (OCA)
Author-email: support@odoo-community.org
Classifier: Programming Language :: Python
Classifier: Framework :: Odoo
Classifier: Framework :: Odoo :: 17.0
Classifier: License :: OSI Approved :: GNU Affero General Public License v3
